rogue_scholar_api/__init__.py
rogue_scholar_api/blogs.py
rogue_scholar_api/posts.py
rogue_scholar_api/schema.py
rogue_scholar_api/supabase.py
rogue_scholar_api/typesense.py
rogue_scholar_api/utils.py
rogue_scholar_api-0.7.1.dist-info/LICENSE
rogue_scholar_api-0.7.1.dist-info/METADATA
rogue_scholar_api-0.7.1.dist-info/WHEEL
rogue_scholar_api-0.7.1.dist-info/entry_points.txt
rogue_scholar_api-0.7.1.dist-info/RECORD
