Metadata-Version: 2.1
Name: rogue-scholar-api
Version: 0.7.1
Summary: API for the Rogue Scholar science blogging platform.
Home-page: https://rogue-scholar.org
License: MIT
Keywords: science,blogging,quart,api,supabase,typesense
Author: Martin Fenner
Author-email: martin@front-matter.io
Requires-Python: >=3.10,<4.0
Classifier: License :: OSI Approved :: MIT License
Classifier: Programming Language :: Python :: 3
Classifier: Programming Language :: Python :: 3.10
Classifier: Programming Language :: Python :: 3.11
Requires-Dist: Quart (>=0.19.2,<0.20.0)
Requires-Dist: aiodns (>=3.1.1,<4.0.0)
Requires-Dist: aiohttp (>=3.8.6,<4.0.0)
Requires-Dist: beautifulsoup4 (>=4.12.2,<5.0.0)
Requires-Dist: chardet (>=5.2.0,<6.0.0)
Requires-Dist: commonmeta-py (>=0.8.4,<0.9.0)
Requires-Dist: feedparser (>=6.0.10,<7.0.0)
Requires-Dist: furl (>=2.1.3,<3.0.0)
Requires-Dist: hypercorn (>=0.14.4,<0.15.0)
Requires-Dist: idutils (>=1.2.1,<2.0.0)
Requires-Dist: iso8601 (>=2.1.0,<3.0.0)
Requires-Dist: nh3 (>=0.2.14,<0.3.0)
Requires-Dist: pydash (>=6.0,<7.0)
Requires-Dist: pytest-asyncio (>=0.21.1,<0.22.0)
Requires-Dist: python-dotenv (>=1.0.0,<2.0.0)
Requires-Dist: quart-rate-limiter (>=0.9.0,<0.10.0)
Requires-Dist: quart-schema (>=0.17.1,<0.18.0)
Requires-Dist: sentry-sdk (>=1.32.0,<2.0.0)
Requires-Dist: supabase (>=1.1.1,<2.0.0)
Requires-Dist: tox (>=4.11.3,<5.0.0)
Requires-Dist: typesense (>=0.17.0,<0.18.0)
Requires-Dist: xmltodict (>=0.12.0,<0.13.0)
Project-URL: Repository, https://github.com/front-matter/rogue-scholar-api
